{
	"titles": [
		"UwU"
	],
	"images": [
	{"url": "https://static.wikia.nocookie.net/codelyoko/images/b/bc/Evo_100.png/revision/latest/scale-to-width-down/1000?cb=20190403163118",
		"source": "https://codelyoko.fandom.com/wiki/Odd_Della_Robbia"},
	{"url": "https://d.facdn.net/art/twiggihighwind/1299815489/1299815489.twiggihighwind_odd__2_.png",
		"source": "https://www.furaffinity.net/view/5384885/", "author": "twiggihighwind"},
	{"url": "https://cdn.weeb.sh/images/H1NKh0uDW.gif"},
	{"url": "https://cdn.weeb.sh/images/Hkaw2AdwZ.jpeg"},
	{"url": "https://cdn.weeb.sh/images/HylGb3AOP-.jpeg"},
	{"url": "https://cdn.weeb.sh/images/HyzSn0OP-.png"},
	{"url": "https://cdn.weeb.sh/images/rk_q4UPu-.jpeg"},
	{"url": "https://cdn.weeb.sh/images/rye5L3C_vZ.jpeg"},
	{"url": "https://cdn.weeb.sh/images/ryLkHJ3qz.jpeg"},
	{"url": "https://cdn.weeb.sh/images/S1-2BhAdv-.jpeg"}
	]
}
